project/__init__.py
project/settings-home.py
project/settings-local.py
project/settings-remote.py
project/settings.py
project/urls.py
sitelfl/__init__.py
sitelfl/management/__init__.py
sitelfl/management/commands/__init__.py
sitelfl/management/commands/check_and_copy_dumps.py
sitelfl/management/commands/check_git_commit.py
sitelfl/management/commands/check_image_files.py
sitelfl/management/commands/check_old_files.py
sitelfl/management/commands/check_relevaant_image_files.py
sitelfl/management/commands/copy_last_dump_to_lfl_db_container.py
sitelfl/management/commands/fill_images.py
sitelfl/management/commands/make_debug_urls.py
sitelfl/management/commands/migrate-base.py
sitelfl/management/commands/restore_bottom_menu.py
sitelfl/management/commands/restore_regferee.py
sitelfl/management/commands/restore_table.py
sitelfl/management/commands/sync_lfl_base.py
sitelfl/management/commands/update_site_lfl.py
sitelfl/migrations/0001_initial.py
sitelfl/migrations/0002_recreated_urls_table_name.py
sitelfl/migrations/0003_alter_recreated_urls_id.py
sitelfl/migrations/0004_auto_20210916_1153.py
sitelfl/migrations/0005_auto_20210916_1155.py
sitelfl/migrations/0006_auto_20210920_0910.py
sitelfl/migrations/__init__.py
sitelfl/models/__init__.py
sitelfl/models/administrators.py
sitelfl/models/assists.py
sitelfl/models/banners.py
sitelfl/models/bottom_menu.py
sitelfl/models/calendar.py
sitelfl/models/cards.py
sitelfl/models/cities.py
sitelfl/models/city_regions.py
sitelfl/models/club_admins.py
sitelfl/models/club_contacts.py
sitelfl/models/club_histories.py
sitelfl/models/club_logo_history.py
sitelfl/models/clubs.py
sitelfl/models/contacts.py
sitelfl/models/discvalification_zones.py
sitelfl/models/disqualifications.py
sitelfl/models/divisions.py
sitelfl/models/fields.py
sitelfl/models/fines.py
sitelfl/models/formation.py
sitelfl/models/fouls.py
sitelfl/models/goals.py
sitelfl/models/images.py
sitelfl/models/keepers.py
sitelfl/models/leagues.py
sitelfl/models/match_resaults.py
lfl_mysql_migrate-0.0.1.dist-info/LICENSE.txt
lfl_mysql_migrate-0.0.1.dist-info/METADATA
lfl_mysql_migrate-0.0.1.dist-info/WHEEL
lfl_mysql_migrate-0.0.1.dist-info/entry_points.txt
lfl_mysql_migrate-0.0.1.dist-info/top_level.txt
lfl_mysql_migrate-0.0.1.dist-info/RECORD
