Metadata-Version: 2.1
Name: lfl-mysql-migrate
Version: 0.0.1
Summary: ISC Python common project
Home-page: UNKNOWN
Author: Andrey Yudin
Author-email: uag@ivc-inform.ru
License: UNKNOWN
Project-URL: Source, https://github.com/lfl-ru/lfl-mysql-migrate.git
Keywords: isc setuptools development common
Platform: UNKNOWN
Classifier: Development Status :: 3 - Alpha
Classifier: Intended Audience :: Developers
Classifier: Topic :: Software Development :: Build Tools
Classifier: License :: OSI Approved :: MIT License
Classifier: Programming Language :: Python :: 3.8
Requires-Python: >=3.8
